amusic/__init__.py
amusic/visualizer.py
amusic-2.4.5.dist-info/licenses/LICENSE
amusic-2.4.5.dist-info/METADATA
amusic-2.4.5.dist-info/WHEEL
amusic-2.4.5.dist-info/top_level.txt
amusic-2.4.5.dist-info/RECORD
