Metadata-Version: 2.4
Name: amusic
Version: 2.4.5
Summary: A MIDI visualizer with VFX.
Home-page: https://github.com/SolamateanTehCoder/amusic
Author: SolamateanTehCoder
Classifier: Programming Language :: Python :: 3
Classifier: License :: OSI Approved :: MIT License
Classifier: Operating System :: OS Independent
Requires-Python: >=3.6
License-File: LICENSE
Requires-Dist: mido
Requires-Dist: pygame
Dynamic: author
Dynamic: classifier
Dynamic: description
Dynamic: description-content-type
Dynamic: home-page
Dynamic: license-file
Dynamic: requires-dist
Dynamic: requires-python
Dynamic: summary
